gpiozero_shiftregister/__init__.py
gpiozero_shiftregister/shiftregister_output.py
gpiozero_shiftregister-0.1.0a0.dist-info/LICENSE
gpiozero_shiftregister-0.1.0a0.dist-info/WHEEL
gpiozero_shiftregister-0.1.0a0.dist-info/METADATA
gpiozero_shiftregister-0.1.0a0.dist-info/RECORD
